anonfile/__init__.py
anonfile/anonfile.py
anonfile-1.0.0.dist-info/LICENSE
anonfile-1.0.0.dist-info/METADATA
anonfile-1.0.0.dist-info/WHEEL
anonfile-1.0.0.dist-info/entry_points.txt
anonfile-1.0.0.dist-info/top_level.txt
anonfile-1.0.0.dist-info/RECORD
