Metadata-Version: 2.1
Name: anonfile
Version: 1.0.0
Summary: An unofficial library that wraps the anonfile.com REST API.
Home-page: https://github.com/nstrydom2/anonfile-api
Author: Nicholas Strydom
Author-email: nstrydom@gmail.com
License: UNKNOWN
Project-URL: Source Code, https://github.com/nstrydom2/anonfile-api
Project-URL: Bug Reports, https://github.com/nstrydom2/anonfile-api/issues
Project-URL: Changelog, https://github.com/nstrydom2/anonfile-api/blob/master/CHANGELOG.md
Keywords: anonfile rest api
Platform: UNKNOWN
Classifier: Programming Language :: Python :: 3.8
Classifier: Programming Language :: Python :: 3.9
Classifier: Programming Language :: Python :: 3.10
Classifier: Programming Language :: Python :: 3.11
Classifier: Intended Audience :: Developers
Classifier: Natural Language :: English
Classifier: Topic :: Internet :: WWW/HTTP :: Dynamic Content
Classifier: Topic :: Software Development :: Libraries
Classifier: Topic :: Utilities
Classifier: License :: OSI Approved :: MIT License
Classifier: Operating System :: OS Independent
Requires-Python: >=3.8
